temul/__init__.py
temul/_version.py
temul/_version_save.py
temul/api.py
temul/api_with_prismatic.py
temul/atomap_devel_temp.py
temul/dummy_data.py
temul/element_tools.py
temul/example_data.py
temul/example_scripts.py
temul/intensity_tools.py
temul/io.py
temul/lattice_structure_tools.py
temul/model_creation.py
temul/model_refiner.py
temul/polarisation.py
temul/signal_plotting.py
temul/signal_processing.py
temul/simulations.py
temul/spectroscopy.py
temul/example_data/experimental/example_Au_nanoparticle.emd
temul/example_data/experimental/example_Se_implanted_MoS2.dm3
temul/example_data/prismatic/MoS2_hex_prismatic.xyz
temul/example_data/prismatic/calibrated_data_probeStep0.01_interpolationFactor4_crop0.5.hspy
temul/example_data/prismatic/example_MoS2_vesta_xyz.xyz
temul/example_data/structures/example_Cu_nanoparticle_sim.hspy
temul/external/atomap_devel_012/__init__.py
temul/external/atomap_devel_012/analysis_tools.py
temul/external/atomap_devel_012/api.py
temul/external/atomap_devel_012/atom_finding_refining.py
temul/external/atomap_devel_012/atom_lattice.py
temul/external/atomap_devel_012/atom_plane.py
temul/external/atomap_devel_012/atom_position.py
temul/external/atomap_devel_012/atom_position_old.py
temul/external/atomap_devel_012/dummy_data.py
temul/external/atomap_devel_012/example_data.py
temul/external/atomap_devel_012/fitting_tools.py
temul/external/atomap_devel_012/gui_classes.py
temul/external/atomap_devel_012/initial_position_finding.py
temul/external/atomap_devel_012/io.py
temul/external/atomap_devel_012/main.py
temul/external/atomap_devel_012/plotting.py
temul/external/atomap_devel_012/process_parameters.py
temul/external/atomap_devel_012/quantification.py
temul/external/atomap_devel_012/stats.py
temul/external/atomap_devel_012/sublattice.py
temul/external/atomap_devel_012/symmetry_finding.py
temul/external/atomap_devel_012/testing_tools.py
temul/external/atomap_devel_012/tools.py
temul/external/atomap_devel_012/external/__init__.py
temul_toolkit-0.1.7.dist-info/LICENSE
temul_toolkit-0.1.7.dist-info/METADATA
temul_toolkit-0.1.7.dist-info/WHEEL
temul_toolkit-0.1.7.dist-info/top_level.txt
temul_toolkit-0.1.7.dist-info/RECORD
