Metadata-Version: 2.1
Name: temul-toolkit
Version: 0.1.7
Summary: Functions for analysis of high resolution electron microscopy and spectroscopy data.
Home-page: https://temul-toolkit.readthedocs.io/
Author: Eoghan N O'Connell
Author-email: eoclives@hotmail.com
License: GPL v3
Keywords: STEM,data analysis,microscopy,data science,image simulation,atomic models
Platform: UNKNOWN
Classifier: Development Status :: 3 - Alpha
Classifier: License :: OSI Approved :: GNU General Public License v3 (GPLv3)
Classifier: Intended Audience :: Science/Research
Classifier: Programming Language :: Python :: 3
Requires-Dist: atomap
Requires-Dist: colorcet
Requires-Dist: glob2
Requires-Dist: hyperspy
Requires-Dist: numpy
Requires-Dist: matplotlib
Requires-Dist: matplotlib-scalebar
Requires-Dist: pandas
Requires-Dist: periodictable
Requires-Dist: scikit-image
Requires-Dist: scipy
Requires-Dist: tifffile
Requires-Dist: tqdm
